{
  "model_path": "/home/openclaw/projects/1ai-poly-trader/backend/ai/models/baseline.pkl",
  "n_examples": 800,
  "feature_order": [
    "edge",
    "model_probability",
    "market_probability",
    "whale_pressure",
    "sentiment",
    "volume_log"
  ],
  "coefficients": [
    0.0,
    0.10328004409617711,
    0.10328004409617711,
    0.0,
    0.0,
    -0.0574651262140074
  ],
  "intercept": 0.2071371973672242,
  "train_accuracy": 0.56375,
  "version": "logreg-1.0",
  "synthetic_data": false
}